ecp/__init__.py
ecp/__main__.py
ecp/genasdot.py
ecp/lexer.py
ecp/parser.py
ecp/parser_helpers.py
ecp/topython.py
ecp/tracker.py
py_ecp-1.5.0.dist-info/LICENCE.md
py_ecp-1.5.0.dist-info/METADATA
py_ecp-1.5.0.dist-info/WHEEL
py_ecp-1.5.0.dist-info/entry_points.txt
py_ecp-1.5.0.dist-info/top_level.txt
py_ecp-1.5.0.dist-info/RECORD
