Metadata-Version: 2.1
Name: py-ecp
Version: 1.5.0
Summary: ECP programming language
Home-page: https://github.com/ecp-lang/ecp-interpreter
Author: Conqu3red
Requires-Python: >=3.6
License-File: LICENCE.md
Requires-Dist: tabulate
Requires-Dist: astor
Requires-Dist: parsergen ==2.0.0b10
